{"1": {"T Min Time": "2017-04-01 22:06", "T Max": "17.3", "Temperature": "12.7", "SunShine": "", "T Min": "11.1", "StnPresMaxTime": "2017-04-01 23:36", "T Max Time": "2017-04-01 10:09", "PrecpHrMaxTime": "", "SunShineRate": "", "PrecpHour ": "", "WSGust": "7.3", "PrecpMax10": "", "WGustTime": "2017-04-01 05:03", "WS   ": "1.3", "RH": "", "WD   ": "39", "PrecpHrMax": "", "EvapA": "", "ObsTime": "1", "RHMin": "X", "SeaPres": "", "StnPres": "951.0", "Td dew point": "", "VisbMean": "", "StnPresMin": "948.5", "StnPresMax": "953.5", "Precp": "14.0", "GloblRad": "", "PrecpMax10Time": "", "RHMinTime": "", "WDGust": "31", "StnPresMinTime": "2017-04-01 03:40"}, "3": {"T Min Time": "2017-04-03 04:11", "T Max": "22.6", "Temperature": "15.9", "SunShine": "", "T Min": "12.1", "StnPresMaxTime": "2017-04-03 08:55", "T Max Time": "2017-04-03 08:41", "PrecpHrMaxTime": "", "SunShineRate": "", "PrecpHour ": "", "WSGust": "5.7", "PrecpMax10": "", "WGustTime": "2017-04-03 11:35", "WS   ": "0.8", "RH": "", "WD   ": "52", "PrecpHrMax": "", "EvapA": "", "ObsTime": "3", "RHMin": "X", "SeaPres": "", "StnPres": "955.3", "Td dew point": "", "VisbMean": "", "StnPresMin": "953.9", "StnPresMax": "957.0", "Precp": "0.0", "GloblRad": "", "PrecpMax10Time": "", "RHMinTime": "", "WDGust": "74", "StnPresMinTime": "2017-04-03 14:36"}, "2": {"T Min Time": "2017-04-02 06:45", "T Max": "21.2", "Temperature": "14.8", "SunShine": "", "T Min": "11.0", "StnPresMaxTime": "2017-04-02 09:37", "T Max Time": "2017-04-02 11:54", "PrecpHrMaxTime": "", "SunShineRate": "", "PrecpHour ": "", "WSGust": "9.1", "PrecpMax10": "", "WGustTime": "2017-04-02 13:26", "WS   ": "1.5", "RH": "", "WD   ": "43", "PrecpHrMax": "", "EvapA": "", "ObsTime": "2", "RHMin": "X", "SeaPres": "", "StnPres": "954.6", "Td dew point": "", "VisbMean": "", "StnPresMin": "952.8", "StnPresMax": "955.9", "Precp": "0.0", "GloblRad": "", "PrecpMax10Time": "", "RHMinTime": "", "WDGust": "58", "StnPresMinTime": "2017-04-02 02:45"}, "5": {"T Min Time": "2017-04-05 04:37", "T Max": "24.6", "Temperature": "19.4", "SunShine": "", "T Min": "14.2", "StnPresMaxTime": "2017-04-05 00:05", "T Max Time": "2017-04-05 10:48", "PrecpHrMaxTime": "", "SunShineRate": "", "PrecpHour ": "", "WSGust": "4.5", "PrecpMax10": "", "WGustTime": "2017-04-05 13:27", "WS   ": "0.6", "RH": "", "WD   ": "235", "PrecpHrMax": "", "EvapA": "", "ObsTime": "5", "RHMin": "X", "SeaPres": "", "StnPres": "950.0", "Td dew point": "", "VisbMean": "", "StnPresMin": "948.0", "StnPresMax": "952.1", "Precp": "0.0", "GloblRad": "", "PrecpMax10Time": "", "RHMinTime": "", "WDGust": "43", "StnPresMinTime": "2017-04-05 15:31"}, "4": {"T Min Time": "2017-04-04 03:40", "T Max": "21.4", "Temperature": "16.9", "SunShine": "", "T Min": "12.1", "StnPresMaxTime": "2017-04-04 08:04", "T Max Time": "2017-04-04 14:20", "PrecpHrMaxTime": "", "SunShineRate": "", "PrecpHour ": "", "WSGust": "2.8", "PrecpMax10": "", "WGustTime": "2017-04-04 14:49", "WS   ": "0.3", "RH": "", "WD   ": "219", "PrecpHrMax": "", "EvapA": "", "ObsTime": "4", "RHMin": "X", "SeaPres": "", "StnPres": "953.2", "Td dew point": "", "VisbMean": "", "StnPresMin": "951.4", "StnPresMax": "955.1", "Precp": "0.0", "GloblRad": "", "PrecpMax10Time": "", "RHMinTime": "", "WDGust": "315", "StnPresMinTime": "2017-04-04 15:05"}, "7": {"T Min Time": "", "T Max": "", "Temperature": "", "SunShine": "", "T Min": "", "StnPresMaxTime": "", "T Max Time": "", "PrecpHrMaxTime": "", "SunShineRate": "", "PrecpHour ": "", "WSGust": "", "PrecpMax10": "", "WGustTime": "", "WS   ": "", "RH": "", "WD   ": "", "PrecpHrMax": "", "EvapA": "", "ObsTime": "7", "RHMin": "", "SeaPres": "", "StnPres": "", "Td dew point": "", "VisbMean": "", "StnPresMin": "", "StnPresMax": "", "Precp": "X", "GloblRad": "", "PrecpMax10Time": "", "RHMinTime": "", "WDGust": "", "StnPresMinTime": ""}, "6": {"T Min Time": "", "T Max": "", "Temperature": "14.6", "SunShine": "", "T Min": "", "StnPresMaxTime": "", "T Max Time": "", "PrecpHrMaxTime": "", "SunShineRate": "", "PrecpHour ": "", "WSGust": "", "PrecpMax10": "", "WGustTime": "", "WS   ": "0.3", "RH": "", "WD   ": "225", "PrecpHrMax": "", "EvapA": "", "ObsTime": "6", "RHMin": "", "SeaPres": "", "StnPres": "948.0", "Td dew point": "", "VisbMean": "", "StnPresMin": "", "StnPresMax": "", "Precp": "0.0", "GloblRad": "", "PrecpMax10Time": "", "RHMinTime": "", "WDGust": "", "StnPresMinTime": ""}, "9": {"T Min Time": "", "T Max": "", "Temperature": "22.6", "SunShine": "", "T Min": "", "StnPresMaxTime": "", "T Max Time": "", "PrecpHrMaxTime": "", "SunShineRate": "", "PrecpHour ": "", "WSGust": "", "PrecpMax10": "", "WGustTime": "", "WS   ": "0.5", "RH": "X", "WD   ": "55", "PrecpHrMax": "", "EvapA": "", "ObsTime": "9", "RHMin": "", "SeaPres": "", "StnPres": "942.3", "Td dew point": "", "VisbMean": "", "StnPresMin": "", "StnPresMax": "", "Precp": "0.0", "GloblRad": "", "PrecpMax10Time": "", "RHMinTime": "", "WDGust": "", "StnPresMinTime": ""}, "8": {"T Min Time": "", "T Max": "", "Temperature": "", "SunShine": "", "T Min": "", "StnPresMaxTime": "", "T Max Time": "", "PrecpHrMaxTime": "", "SunShineRate": "", "PrecpHour ": "", "WSGust": "", "PrecpMax10": "", "WGustTime": "", "WS   ": "", "RH": "", "WD   ": "", "PrecpHrMax": "", "EvapA": "", "ObsTime": "8", "RHMin": "", "SeaPres": "", "StnPres": "", "Td dew point": "", "VisbMean": "", "StnPresMin": "", "StnPresMax": "", "Precp": "X", "GloblRad": "", "PrecpMax10Time": "", "RHMinTime": "", "WDGust": "", "StnPresMinTime": ""}}